README.rst
redmusic.zip
screenshot.png
setup.py
docs/HISTORY.txt
docs/INSTALL.txt
docs/LICENSE.GPL
docs/LICENSE.txt
plonetheme/__init__.py
plonetheme.redmusic.egg-info/PKG-INFO
plonetheme.redmusic.egg-info/SOURCES.txt
plonetheme.redmusic.egg-info/dependency_links.txt
plonetheme.redmusic.egg-info/entry_points.txt
plonetheme.redmusic.egg-info/namespace_packages.txt
plonetheme.redmusic.egg-info/requires.txt
plonetheme.redmusic.egg-info/top_level.txt
plonetheme/redmusic/__init__.py
plonetheme/redmusic/configure.zcml
plonetheme/redmusic/profiles/default/metadata.xml
plonetheme/redmusic/profiles/default/theme.xml
plonetheme/redmusic/static/index.html
plonetheme/redmusic/static/license.txt
plonetheme/redmusic/static/manifest.cfg
plonetheme/redmusic/static/plone-integration.css
plonetheme/redmusic/static/rules.xml
plonetheme/redmusic/static/style.css
plonetheme/redmusic/static/images/body.gif
plonetheme/redmusic/static/images/body_bckg.gif
plonetheme/redmusic/static/images/footer_bckg.jpg
plonetheme/redmusic/static/images/li.gif
plonetheme/redmusic/static/images/main_bckg.jpg